{
  "updated_at": "2026-03-24T23:31:00+00:00",
  "regions": [
    {
      "region": "Europe",
      "session_name": "EUROPE",
      "session_start": "24/03/2026 04:00",
      "updated_at": "2026-03-24T06:46:00+00:00",
      "versions": [
        {
          "region": "Europe",
          "version": "1.2.2",
          "vies": "FORA",
          "score": 0.23,
          "motivo": "EURUSD: FORA (score=0.23) | Tendencia: Alta (H4: slopes EMA20/EMA50 positivos e preco acima das medias.; D1: preco abaixo da EMA20 (-0.5).); Contexto: Desfavoravel (D1: preco abaixo da EMA20 (-1).; D1: preco abaixo da EMA50 (-0.5).) | Alertas: Baixa volatilidade: range < 1.0x ATR.",
          "hit": true,
          "hit_ref_time": "2026-02-03T00:00:00",
          "updated_at": "2026-03-24T06:46:00+00:00",
          "symbol_results": [
            {
              "symbol": "EURUSD",
              "vies": "FORA",
              "score": 0.23,
              "motivos": [
                "Tendencia: Alta (H4: slopes EMA20/EMA50 positivos e preco acima das medias.; D1: preco abaixo da EMA20 (-0.5).)",
                "Contexto: Desfavoravel (D1: preco abaixo da EMA20 (-1).; D1: preco abaixo da EMA50 (-0.5).)",
                "Impulso: Moderado (ADX=25.5 entre 21-33 (+1).; Impulso segue a tendência (a favor da alta).)",
                "Mitigação: Atenção: mercado travado (Candle atual < 1.0x ATR (-1).)"
              ],
              "alertas": [
                "Baixa volatilidade: range < 1.0x ATR."
              ],
              "blocos": {
                "tendencia": {
                  "score": 1.5,
                  "status": "Alta",
                  "notas": [
                    "H4: slopes EMA20/EMA50 positivos e preco acima das medias.",
                    "D1: preco abaixo da EMA20 (-0.5)."
                  ],
                  "valores": {
                    "timeframe": "H4",
                    "slope_ema20": 0.00027016536063013063,
                    "slope_ema50": 0.00013715959523713048,
                    "preco": 1.15831,
                    "ema20": 1.1566420528167418,
                    "ema50": 1.1550101769107561
                  }
                },
                "contexto": {
                  "score": -1.5,
                  "status": "Desfavoravel",
                  "notas": [
                    "D1: preco abaixo da EMA20 (-1).",
                    "D1: preco abaixo da EMA50 (-0.5)."
                  ],
                  "valores": {
                    "timeframe": "D1",
                    "vwap": 1.1577881214649979,
                    "ema20": 1.1588377535779628,
                    "ema50": 1.166047451967819,
                    "atr": 0.009038377167788188,
                    "context_blocked": false
                  }
                },
                "impulso": {
                  "score": 1.0,
                  "status": "Moderado",
                  "notas": [
                    "ADX=25.5 entre 21-33 (+1).",
                    "Impulso segue a tendência (a favor da alta)."
                  ],
                  "valores": {
                    "adx": 25.48929380607899
                  }
                },
                "mitigacao": {
                  "score": -1.0,
                  "status": "Atenção: mercado travado",
                  "notas": [
                    "Candle atual < 1.0x ATR (-1)."
                  ],
                  "valores": {
                    "candle_range": 0.00019999999999997797,
                    "atr": 0.0005394817060870601,
                    "mitigation_blocked": false
                  }
                }
              },
              "hit": null,
              "ref_time": "2026-03-24T06:30:00+00:00"
            }
          ],
          "accuracy": 0.9036144578313253
        },
        {
          "region": "Europe",
          "version": "1.0.2",
          "vies": "FORA",
          "score": 0.23,
          "motivo": "EURUSD: FORA (score=0.23) | Tendencia: Alta (H4: slopes EMA20/EMA50 positivos e preco acima das medias.; D1: preco abaixo da EMA20 (-0.5).); Contexto: Desfavoravel (D1: preco abaixo da EMA20 (-1).; D1: preco abaixo da EMA50 (-0.5).) | Alertas: Baixa volatilidade: range < 1.2x ATR.",
          "hit": false,
          "hit_ref_time": "2026-01-15T00:00:00",
          "updated_at": "2026-03-24T06:46:00+00:00",
          "symbol_results": [
            {
              "symbol": "EURUSD",
              "vies": "FORA",
              "score": 0.23,
              "motivos": [
                "Tendencia: Alta (H4: slopes EMA20/EMA50 positivos e preco acima das medias.; D1: preco abaixo da EMA20 (-0.5).)",
                "Contexto: Desfavoravel (D1: preco abaixo da EMA20 (-1).; D1: preco abaixo da EMA50 (-0.5).)",
                "Impulso: Moderado (ADX=25.5 entre 21-30 (+1).; Impulso segue a tendência (a favor da alta).)",
                "Mitigação: Atenção: mercado travado (Candle atual < 1.2x ATR (-1).)"
              ],
              "alertas": [
                "Baixa volatilidade: range < 1.2x ATR."
              ],
              "blocos": {
                "tendencia": {
                  "score": 1.5,
                  "status": "Alta",
                  "notas": [
                    "H4: slopes EMA20/EMA50 positivos e preco acima das medias.",
                    "D1: preco abaixo da EMA20 (-0.5)."
                  ],
                  "valores": {
                    "timeframe": "H4",
                    "slope_ema20": 0.00027016536063013063,
                    "slope_ema50": 0.00013715959523713048,
                    "preco": 1.15831,
                    "ema20": 1.1566420528167418,
                    "ema50": 1.1550101769107561
                  }
                },
                "contexto": {
                  "score": -1.5,
                  "status": "Desfavoravel",
                  "notas": [
                    "D1: preco abaixo da EMA20 (-1).",
                    "D1: preco abaixo da EMA50 (-0.5)."
                  ],
                  "valores": {
                    "timeframe": "D1",
                    "vwap": 1.1577881214649979,
                    "ema20": 1.1588377535779628,
                    "ema50": 1.166047451967819,
                    "atr": 0.009038377167788188,
                    "context_blocked": false
                  }
                },
                "impulso": {
                  "score": 1.0,
                  "status": "Moderado",
                  "notas": [
                    "ADX=25.5 entre 21-30 (+1).",
                    "Impulso segue a tendência (a favor da alta)."
                  ],
                  "valores": {
                    "adx": 25.48929380607899
                  }
                },
                "mitigacao": {
                  "score": -1.0,
                  "status": "Atenção: mercado travado",
                  "notas": [
                    "Candle atual < 1.2x ATR (-1)."
                  ],
                  "valores": {
                    "candle_range": 0.00019999999999997797,
                    "atr": 0.0005394817060870601,
                    "mitigation_blocked": false
                  }
                }
              },
              "hit": null,
              "ref_time": "2026-03-24T06:30:00+00:00"
            }
          ],
          "accuracy": 0.7384615384615385
        }
      ],
      "best_version": {
        "version": "1.2.2",
        "accuracy": 0.9036144578313253
      }
    },
    {
      "region": "America",
      "session_name": "AMERICA",
      "session_start": "24/03/2026 10:30",
      "updated_at": "2026-03-24T13:16:00+00:00",
      "versions": [
        {
          "region": "America",
          "version": "1.2.3",
          "vies": "FORA",
          "score": 0.0,
          "motivo": "XAUUSD: FORA (score=0.0) | Tendencia: Baixa (H4: slopes EMA20/EMA50 negativos e preco abaixo das medias.; D1: preco abaixo da EMA20 (-0.5).); Contexto: Neutro (D1: preco abaixo da EMA20 (-1).; D1: preco abaixo da EMA50 (-0.5).; Preco esticado > 1.0x ATR distante da EMA20 (penaliza para neutro).) | Alertas: Contexto: preco afastado demais da media (risco de correcao).; Sinal vetado por preco afastado e score baixo.",
          "hit": true,
          "hit_ref_time": "2026-01-20T00:00:00",
          "updated_at": "2026-03-24T13:16:00+00:00",
          "symbol_results": [
            {
              "symbol": "XAUUSD",
              "vies": "FORA",
              "score": 0.0,
              "motivos": [
                "Tendencia: Baixa (H4: slopes EMA20/EMA50 negativos e preco abaixo das medias.; D1: preco abaixo da EMA20 (-0.5).)",
                "Contexto: Neutro (D1: preco abaixo da EMA20 (-1).; D1: preco abaixo da EMA50 (-0.5).; Preco esticado > 1.0x ATR distante da EMA20 (penaliza para neutro).)",
                "Impulso: Fraco (ADX=23.0 abaixo de 27 (0).; Impulso segue a tendência (a favor da baixa).)",
                "Mitigação: Sem alertas (Volatilidade dentro do intervalo esperado.)"
              ],
              "alertas": [
                "Contexto: preco afastado demais da media (risco de correcao).",
                "Sinal vetado por preco afastado e score baixo."
              ],
              "blocos": {
                "tendencia": {
                  "score": -2.0,
                  "status": "Baixa",
                  "notas": [
                    "H4: slopes EMA20/EMA50 negativos e preco abaixo das medias.",
                    "D1: preco abaixo da EMA20 (-0.5)."
                  ],
                  "valores": {
                    "timeframe": "H4",
                    "slope_ema20": -18.842796781773473,
                    "slope_ema50": -14.85993132466448,
                    "preco": 4407.54269,
                    "ema20": 4475.001926999366,
                    "ema50": 4671.214156742987
                  }
                },
                "contexto": {
                  "score": -0.5,
                  "status": "Neutro",
                  "notas": [
                    "D1: preco abaixo da EMA20 (-1).",
                    "D1: preco abaixo da EMA50 (-0.5).",
                    "Preco esticado > 1.0x ATR distante da EMA20 (penaliza para neutro).",
                    "Veto: preco afastado e score < 3.0."
                  ],
                  "valores": {
                    "timeframe": "D1",
                    "vwap": 4398.623540867039,
                    "ema20": 4880.1644794437025,
                    "ema50": 4933.163597994763,
                    "atr": 153.19704760513957,
                    "context_blocked": false
                  }
                },
                "impulso": {
                  "score": -0.0,
                  "status": "Fraco",
                  "notas": [
                    "ADX=23.0 abaixo de 27 (0).",
                    "Impulso segue a tendência (a favor da baixa)."
                  ],
                  "valores": {
                    "adx": 22.96826574029764
                  }
                },
                "mitigacao": {
                  "score": 0.0,
                  "status": "Sem alertas",
                  "notas": [
                    "Volatilidade dentro do intervalo esperado."
                  ],
                  "valores": {
                    "candle_range": 16.18489000000045,
                    "atr": 21.95586633623013,
                    "mitigation_blocked": false
                  }
                }
              },
              "hit": null,
              "ref_time": "2026-03-24T13:00:00+00:00"
            }
          ],
          "accuracy": 0.9710144927536232
        },
        {
          "region": "America",
          "version": "1.0.3",
          "vies": "VENDA",
          "score": -3.1,
          "motivo": "XAUUSD: VENDA (score=-3.1) | Tendencia: Baixa (H4: slopes EMA20/EMA50 negativos e preco abaixo das medias.; D1: preco abaixo da EMA20 (-0.5).); Contexto: Neutro (D1: preco abaixo da EMA20 (-1).; D1: preco abaixo da EMA50 (-0.5).; Preco esticado > 0.4x ATR distante da EMA20 (penaliza para neutro).) | Alertas: Contexto: preco afastado demais da media (risco de correcao).",
          "hit": true,
          "hit_ref_time": "2026-01-20T00:00:00",
          "updated_at": "2026-03-24T13:16:00+00:00",
          "symbol_results": [
            {
              "symbol": "XAUUSD",
              "vies": "VENDA",
              "score": -3.1,
              "motivos": [
                "Tendencia: Baixa (H4: slopes EMA20/EMA50 negativos e preco abaixo das medias.; D1: preco abaixo da EMA20 (-0.5).)",
                "Contexto: Neutro (D1: preco abaixo da EMA20 (-1).; D1: preco abaixo da EMA50 (-0.5).; Preco esticado > 0.4x ATR distante da EMA20 (penaliza para neutro).)",
                "Impulso: Moderado (ADX=23.0 entre 7-35 (+1).; Impulso segue a tendência (a favor da baixa).)",
                "Mitigação: Sem alertas (Volatilidade dentro do intervalo esperado.)"
              ],
              "alertas": [
                "Contexto: preco afastado demais da media (risco de correcao)."
              ],
              "blocos": {
                "tendencia": {
                  "score": -2.0,
                  "status": "Baixa",
                  "notas": [
                    "H4: slopes EMA20/EMA50 negativos e preco abaixo das medias.",
                    "D1: preco abaixo da EMA20 (-0.5)."
                  ],
                  "valores": {
                    "timeframe": "H4",
                    "slope_ema20": -18.842796781773473,
                    "slope_ema50": -14.85993132466448,
                    "preco": 4407.54269,
                    "ema20": 4475.001926999366,
                    "ema50": 4671.214156742987
                  }
                },
                "contexto": {
                  "score": -0.5,
                  "status": "Neutro",
                  "notas": [
                    "D1: preco abaixo da EMA20 (-1).",
                    "D1: preco abaixo da EMA50 (-0.5).",
                    "Preco esticado > 0.4x ATR distante da EMA20 (penaliza para neutro)."
                  ],
                  "valores": {
                    "timeframe": "D1",
                    "vwap": 4398.623540867039,
                    "ema20": 4880.1644794437025,
                    "ema50": 4933.163597994763,
                    "atr": 153.19704760513957,
                    "context_blocked": false
                  }
                },
                "impulso": {
                  "score": -1.0,
                  "status": "Moderado",
                  "notas": [
                    "ADX=23.0 entre 7-35 (+1).",
                    "Impulso segue a tendência (a favor da baixa)."
                  ],
                  "valores": {
                    "adx": 22.96826574029764
                  }
                },
                "mitigacao": {
                  "score": 0.0,
                  "status": "Sem alertas",
                  "notas": [
                    "Volatilidade dentro do intervalo esperado."
                  ],
                  "valores": {
                    "candle_range": 16.18489000000045,
                    "atr": 21.95586633623013,
                    "mitigation_blocked": false
                  }
                }
              },
              "hit": null,
              "ref_time": "2026-03-24T13:00:00+00:00"
            }
          ],
          "accuracy": 0.803030303030303
        }
      ],
      "best_version": {
        "version": "1.2.3",
        "accuracy": 0.9710144927536232
      }
    },
    {
      "region": "Asia",
      "session_name": "ASIA",
      "session_start": "24/03/2026 21:00",
      "updated_at": "2026-03-24T23:31:00+00:00",
      "versions": [
        {
          "region": "Asia",
          "version": "1.2.1",
          "vies": "COMPRA",
          "score": 2.74,
          "motivo": "USDJPY: COMPRA (score=2.74) | Tendencia: Neutro (H4: slopes das EMAs proximos de zero.; D1: preco acima da EMA20 (+0.5).); Contexto: Favoravel (D1: preco acima da EMA20 (+1).; D1: preco acima da EMA50 (+0.5).) | Alertas: Baixa volatilidade: range < 0.8x ATR.",
          "hit": true,
          "hit_ref_time": "2026-02-06T00:00:00",
          "updated_at": "2026-03-24T23:31:00+00:00",
          "symbol_results": [
            {
              "symbol": "USDJPY",
              "vies": "COMPRA",
              "score": 2.74,
              "motivos": [
                "Tendencia: Neutro (H4: slopes das EMAs proximos de zero.; D1: preco acima da EMA20 (+0.5).)",
                "Contexto: Favoravel (D1: preco acima da EMA20 (+1).; D1: preco acima da EMA50 (+0.5).)",
                "Impulso: Forte (ADX=35.8 acima de 13 (+2).; Impulso segue a tendência (a favor da alta).)",
                "Mitigação: Atenção: mercado travado (Candle atual < 0.8x ATR (-1).)"
              ],
              "alertas": [
                "Baixa volatilidade: range < 0.8x ATR."
              ],
              "blocos": {
                "tendencia": {
                  "score": 0.5,
                  "status": "Neutro",
                  "notas": [
                    "H4: slopes das EMAs proximos de zero.",
                    "D1: preco acima da EMA20 (+0.5)."
                  ],
                  "valores": {
                    "timeframe": "H4",
                    "slope_ema20": -0.0003024638711095167,
                    "slope_ema50": 0.0028689118095188873,
                    "preco": 158.98917,
                    "ema20": 158.89798141302253,
                    "ema50": 158.91390753397832
                  }
                },
                "contexto": {
                  "score": 1.5,
                  "status": "Favoravel",
                  "notas": [
                    "D1: preco acima da EMA20 (+1).",
                    "D1: preco acima da EMA50 (+0.5)."
                  ],
                  "valores": {
                    "timeframe": "D1",
                    "vwap": 158.72802435378344,
                    "ema20": 158.25574725179882,
                    "ema50": 157.43253628509726,
                    "atr": 1.1648039356125808,
                    "context_blocked": false
                  }
                },
                "impulso": {
                  "score": 2.0,
                  "status": "Forte",
                  "notas": [
                    "ADX=35.8 acima de 13 (+2).",
                    "Impulso segue a tendência (a favor da alta)."
                  ],
                  "valores": {
                    "adx": 35.767230556408556
                  }
                },
                "mitigacao": {
                  "score": -1.0,
                  "status": "Atenção: mercado travado",
                  "notas": [
                    "Candle atual < 0.8x ATR (-1)."
                  ],
                  "valores": {
                    "candle_range": 0.0614800000000173,
                    "atr": 0.10680889278906579,
                    "mitigation_blocked": false
                  }
                }
              },
              "hit": null,
              "ref_time": "2026-03-24T23:15:00+00:00"
            }
          ],
          "accuracy": 0.7222222222222222
        },
        {
          "region": "Asia",
          "version": "1.0.1",
          "vies": "COMPRA",
          "score": 2.74,
          "motivo": "USDJPY: COMPRA (score=2.74) | Tendencia: Neutro (H4: slopes das EMAs proximos de zero.; D1: preco acima da EMA20 (+0.5).); Contexto: Favoravel (D1: preco acima da EMA20 (+1).; D1: preco acima da EMA50 (+0.5).) | Alertas: Baixa volatilidade: range < 1.3x ATR.",
          "hit": true,
          "hit_ref_time": "2026-02-06T00:00:00",
          "updated_at": "2026-03-24T23:31:00+00:00",
          "symbol_results": [
            {
              "symbol": "USDJPY",
              "vies": "COMPRA",
              "score": 2.74,
              "motivos": [
                "Tendencia: Neutro (H4: slopes das EMAs proximos de zero.; D1: preco acima da EMA20 (+0.5).)",
                "Contexto: Favoravel (D1: preco acima da EMA20 (+1).; D1: preco acima da EMA50 (+0.5).)",
                "Impulso: Forte (ADX=35.8 acima de 17 (+2).; Impulso segue a tendência (a favor da alta).)",
                "Mitigação: Atenção: mercado travado (Candle atual < 1.3x ATR (-1).)"
              ],
              "alertas": [
                "Baixa volatilidade: range < 1.3x ATR."
              ],
              "blocos": {
                "tendencia": {
                  "score": 0.5,
                  "status": "Neutro",
                  "notas": [
                    "H4: slopes das EMAs proximos de zero.",
                    "D1: preco acima da EMA20 (+0.5)."
                  ],
                  "valores": {
                    "timeframe": "H4",
                    "slope_ema20": -0.0003024638711095167,
                    "slope_ema50": 0.0028689118095188873,
                    "preco": 158.98917,
                    "ema20": 158.89798141302253,
                    "ema50": 158.91390753397832
                  }
                },
                "contexto": {
                  "score": 1.5,
                  "status": "Favoravel",
                  "notas": [
                    "D1: preco acima da EMA20 (+1).",
                    "D1: preco acima da EMA50 (+0.5)."
                  ],
                  "valores": {
                    "timeframe": "D1",
                    "vwap": 158.72802435378344,
                    "ema20": 158.25574725179882,
                    "ema50": 157.43253628509726,
                    "atr": 1.1648039356125808,
                    "context_blocked": false
                  }
                },
                "impulso": {
                  "score": 2.0,
                  "status": "Forte",
                  "notas": [
                    "ADX=35.8 acima de 17 (+2).",
                    "Impulso segue a tendência (a favor da alta)."
                  ],
                  "valores": {
                    "adx": 35.767230556408556
                  }
                },
                "mitigacao": {
                  "score": -1.0,
                  "status": "Atenção: mercado travado",
                  "notas": [
                    "Candle atual < 1.3x ATR (-1)."
                  ],
                  "valores": {
                    "candle_range": 0.0614800000000173,
                    "atr": 0.10680889278906579,
                    "mitigation_blocked": false
                  }
                }
              },
              "hit": null,
              "ref_time": "2026-03-24T23:15:00+00:00"
            }
          ],
          "accuracy": 0.7391304347826086
        }
      ],
      "best_version": {
        "version": "1.0.1",
        "accuracy": 0.7391304347826086
      }
    }
  ]
}